mario_addons/__init__.py
mario_addons/plugins/__init__.py
mario_addons/plugins/addons.toml
mario_addons/plugins/read.py
mario_addons/plugins/read.toml
mario_addons/plugins/walking.py
mario_addons/plugins/write.py
mario_addons/plugins/write.toml
mario_addons-0.1.29.dist-info/AUTHORS.rst
mario_addons-0.1.29.dist-info/METADATA
mario_addons-0.1.29.dist-info/WHEEL
mario_addons-0.1.29.dist-info/entry_points.txt
mario_addons-0.1.29.dist-info/top_level.txt
mario_addons-0.1.29.dist-info/RECORD
