Metadata-Version: 2.1
Name: mario-addons
Version: 0.1.29
Summary: More commands for Mario.
Home-page: https://github.com/python-mario/mario-addons
Author: Mario contributors
Author-email: email@example.com
License: UNKNOWN
Platform: UNKNOWN
Classifier: Development Status :: 3 - Alpha
Classifier: Intended Audience :: Developers
Classifier: Operating System :: Unix
Classifier: Operating System :: POSIX
Classifier: Operating System :: Microsoft :: Windows
Classifier: Programming Language :: Python
Classifier: Programming Language :: Python :: 3
Classifier: Programming Language :: Python :: 3.6
Classifier: Programming Language :: Python :: 3.7
Classifier: Programming Language :: Python :: Implementation :: CPython
Classifier: Programming Language :: Python :: Implementation :: PyPy
Classifier: Topic :: Utilities
Requires-Dist: pyyaml
Requires-Dist: lxml
Requires-Dist: attr
Requires-Dist: xmltodict
Requires-Dist: mario (==0.0.140)
Provides-Extra: dev
Requires-Dist: ansicolors (==1.0.2); extra == 'dev'
Requires-Dist: appdirs (==1.4.3); extra == 'dev'
Requires-Dist: argh (==0.26.2); extra == 'dev'
Requires-Dist: aspy.yaml (==1.3.0); extra == 'dev'
Requires-Dist: astroid (==2.2.5); extra == 'dev'
Requires-Dist: atomicwrites (==1.3.0); extra == 'dev'
Requires-Dist: attrs (==19.1.0); extra == 'dev'
Requires-Dist: black (==19.3b0); extra == 'dev'
Requires-Dist: bleach (==3.1.0); extra == 'dev'
Requires-Dist: bump2version (==0.5.10); extra == 'dev'
Requires-Dist: certifi (==2019.6.16); extra == 'dev'
Requires-Dist: cfgv (==2.0.1); extra == 'dev'
Requires-Dist: chardet (==3.0.4); extra == 'dev'
Requires-Dist: check-manifest (==0.39); extra == 'dev'
Requires-Dist: click (==7.0); extra == 'dev'
Requires-Dist: coverage (==4.5.3); extra == 'dev'
Requires-Dist: cuvner (==18.0.1); extra == 'dev'
Requires-Dist: docshtest (==0.0.2); extra == 'dev'
Requires-Dist: docutils (==0.15); extra == 'dev'
Requires-Dist: entrypoints (==0.3); extra == 'dev'
Requires-Dist: filelock (==3.0.12); extra == 'dev'
Requires-Dist: flake8 (==3.7.8); extra == 'dev'
Requires-Dist: identify (==1.4.5); extra == 'dev'
Requires-Dist: idna (==2.8); extra == 'dev'
Requires-Dist: importlib-metadata (==0.18); extra == 'dev'
Requires-Dist: incremental (==17.5.0); extra == 'dev'
Requires-Dist: isort (==4.3.21); extra == 'dev'
Requires-Dist: jinja2 (==2.10.1); extra == 'dev'
Requires-Dist: lazy-object-proxy (==1.4.1); extra == 'dev'
Requires-Dist: markupsafe (==1.1.1); extra == 'dev'
Requires-Dist: mccabe (==0.6.1); extra == 'dev'
Requires-Dist: more-itertools (==7.1.0); extra == 'dev'
Requires-Dist: mypy-extensions (==0.4.1); extra == 'dev'
Requires-Dist: mypy (==0.720); extra == 'dev'
Requires-Dist: nodeenv (==1.3.3); extra == 'dev'
Requires-Dist: packaging (==19.0); extra == 'dev'
Requires-Dist: pathtools (==0.1.2); extra == 'dev'
Requires-Dist: pex (==1.6.8); extra == 'dev'
Requires-Dist: pkginfo (==1.5.0.1); extra == 'dev'
Requires-Dist: pluggy (==0.12.0); extra == 'dev'
Requires-Dist: pre-commit (==1.17.0); extra == 'dev'
Requires-Dist: py (==1.8.0); extra == 'dev'
Requires-Dist: pycodestyle (==2.5.0); extra == 'dev'
Requires-Dist: pyflakes (==2.1.1); extra == 'dev'
Requires-Dist: pygments (==2.4.2); extra == 'dev'
Requires-Dist: pylint (==2.3.1); extra == 'dev'
Requires-Dist: pyparsing (==2.4.0); extra == 'dev'
Requires-Dist: pytest-cov (==2.7.1); extra == 'dev'
Requires-Dist: pytest-sphinx (==0.2.2); extra == 'dev'
Requires-Dist: pytest-sugar (==0.9.2); extra == 'dev'
Requires-Dist: pytest (==5.0.1); extra == 'dev'
Requires-Dist: pyyaml (==5.1.1); extra == 'dev'
Requires-Dist: readme-renderer (==24.0); extra == 'dev'
Requires-Dist: requests-toolbelt (==0.9.1); extra == 'dev'
Requires-Dist: requests (==2.22.0); extra == 'dev'
Requires-Dist: six (==1.12.0); extra == 'dev'
Requires-Dist: termcolor (==1.1.0); extra == 'dev'
Requires-Dist: toml (==0.10.0); extra == 'dev'
Requires-Dist: towncrier (==19.2.0); extra == 'dev'
Requires-Dist: tox (==3.13.2); extra == 'dev'
Requires-Dist: tqdm (==4.32.2); extra == 'dev'
Requires-Dist: twine (==1.13.0); extra == 'dev'
Requires-Dist: typed-ast (==1.4.0); extra == 'dev'
Requires-Dist: typing-extensions (==3.7.4); extra == 'dev'
Requires-Dist: unidiff (==0.5.5); extra == 'dev'
Requires-Dist: urllib3 (==1.25.3); extra == 'dev'
Requires-Dist: versioneer (==0.18); extra == 'dev'
Requires-Dist: virtualenv (==16.6.2); extra == 'dev'
Requires-Dist: watchdog (==0.9.0); extra == 'dev'
Requires-Dist: wcwidth (==0.1.7); extra == 'dev'
Requires-Dist: webencodings (==0.5.1); extra == 'dev'
Requires-Dist: wheel (==0.33.4); extra == 'dev'
Requires-Dist: wrapt (==1.11.2); extra == 'dev'
Requires-Dist: zipp (==0.5.2); extra == 'dev'
